testcontainers/clickhouse/__init__.py
tests/test_clickhouse.py
testcontainers_clickhouse-0.0.1rc1.dist-info/METADATA
testcontainers_clickhouse-0.0.1rc1.dist-info/WHEEL
testcontainers_clickhouse-0.0.1rc1.dist-info/top_level.txt
testcontainers_clickhouse-0.0.1rc1.dist-info/RECORD
